{
  "generatedAt": "2026-06-22T09:00:08.291255+00:00",
  "sourceDirectory": "../drive-test-assistant/output/downloads",
  "rows": [
    {
      "testType": "G",
      "testCentre": "Barrie",
      "availableDate": "2026-07-24",
      "availableDateLabel": "July 24, 2026",
      "updatedAt": "2026-06-21T20:11:15-04:00",
      "updatedAtEpochMs": 1782087075000
    },
    {
      "testType": "G",
      "testCentre": "Burlington",
      "availableDate": "2026-07-28",
      "availableDateLabel": "July 28, 2026",
      "updatedAt": "2026-06-21T17:54:24-04:00",
      "updatedAtEpochMs": 1782078864000
    },
    {
      "testType": "G",
      "testCentre": "Kitchener",
      "availableDate": "2026-07-27",
      "availableDateLabel": "July 27, 2026",
      "updatedAt": "2026-06-21T20:26:24-04:00",
      "updatedAtEpochMs": 1782087984000
    },
    {
      "testType": "G",
      "testCentre": "Lindsay",
      "availableDate": "2026-07-29",
      "availableDateLabel": "July 29, 2026",
      "updatedAt": "2026-06-21T20:14:51-04:00",
      "updatedAtEpochMs": 1782087291000
    },
    {
      "testType": "G",
      "testCentre": "Mississauga",
      "availableDate": "2026-07-29",
      "availableDateLabel": "July 29, 2026",
      "updatedAt": "2026-06-21T18:15:19-04:00",
      "updatedAtEpochMs": 1782080119000
    },
    {
      "testType": "G",
      "testCentre": "Newmarket",
      "availableDate": "2026-07-27",
      "availableDateLabel": "July 27, 2026",
      "updatedAt": "2026-06-21T18:56:41-04:00",
      "updatedAtEpochMs": 1782082601000
    },
    {
      "testType": "G",
      "testCentre": "Oakville",
      "availableDate": "2026-06-22",
      "availableDateLabel": "June 22, 2026",
      "updatedAt": "2026-06-21T18:42:15-04:00",
      "updatedAtEpochMs": 1782081735000
    },
    {
      "testType": "G",
      "testCentre": "Smiths Falls",
      "availableDate": "2026-07-28",
      "availableDateLabel": "July 28, 2026",
      "updatedAt": "2026-06-21T19:49:58-04:00",
      "updatedAtEpochMs": 1782085798000
    },
    {
      "testType": "G",
      "testCentre": "Toronto Etobicoke",
      "availableDate": "2026-07-27",
      "availableDateLabel": "July 27, 2026",
      "updatedAt": "2026-06-21T17:33:20-04:00",
      "updatedAtEpochMs": 1782077600000
    },
    {
      "testType": "G",
      "testCentre": "Toronto Port Union",
      "availableDate": "2026-06-23",
      "availableDateLabel": "June 23, 2026",
      "updatedAt": "2026-06-21T19:50:09-04:00",
      "updatedAtEpochMs": 1782085809000
    },
    {
      "testType": "G2",
      "testCentre": "Barrie",
      "availableDate": "2026-06-22",
      "availableDateLabel": "June 22, 2026",
      "updatedAt": "2026-06-21T18:32:36-04:00",
      "updatedAtEpochMs": 1782081156000
    },
    {
      "testType": "G2",
      "testCentre": "Burlington",
      "availableDate": "2026-07-24",
      "availableDateLabel": "July 24, 2026",
      "updatedAt": "2026-06-21T18:40:35-04:00",
      "updatedAtEpochMs": 1782081635000
    },
    {
      "testType": "G2",
      "testCentre": "Guelph",
      "availableDate": "2026-07-22",
      "availableDateLabel": "July 22, 2026",
      "updatedAt": "2026-06-21T17:53:13-04:00",
      "updatedAtEpochMs": 1782078793000
    },
    {
      "testType": "G2",
      "testCentre": "Lindsay",
      "availableDate": "2026-06-22",
      "availableDateLabel": "June 22, 2026",
      "updatedAt": "2026-06-21T19:53:54-04:00",
      "updatedAtEpochMs": 1782086034000
    },
    {
      "testType": "G2",
      "testCentre": "Newmarket",
      "availableDate": "2026-07-29",
      "availableDateLabel": "July 29, 2026",
      "updatedAt": "2026-06-21T18:33:39-04:00",
      "updatedAtEpochMs": 1782081219000
    },
    {
      "testType": "G2",
      "testCentre": "Oakville",
      "availableDate": "2026-07-28",
      "availableDateLabel": "July 28, 2026",
      "updatedAt": "2026-06-21T18:57:51-04:00",
      "updatedAtEpochMs": 1782082671000
    },
    {
      "testType": "G2",
      "testCentre": "Orillia",
      "availableDate": "2026-06-30",
      "availableDateLabel": "June 30, 2026",
      "updatedAt": "2026-06-21T20:04:19-04:00",
      "updatedAtEpochMs": 1782086659000
    },
    {
      "testType": "G2",
      "testCentre": "Peterborough",
      "availableDate": "2026-07-13",
      "availableDateLabel": "July 13, 2026",
      "updatedAt": "2026-06-21T20:38:33-04:00",
      "updatedAtEpochMs": 1782088713000
    },
    {
      "testType": "G2",
      "testCentre": "Renfrew",
      "availableDate": "2026-07-24",
      "availableDateLabel": "July 24, 2026",
      "updatedAt": "2026-06-21T18:06:31-04:00",
      "updatedAtEpochMs": 1782079591000
    },
    {
      "testType": "G2",
      "testCentre": "Smiths Falls",
      "availableDate": "2026-06-23",
      "availableDateLabel": "June 23, 2026",
      "updatedAt": "2026-06-21T20:25:09-04:00",
      "updatedAtEpochMs": 1782087909000
    },
    {
      "testType": "G2",
      "testCentre": "Toronto Downsview",
      "availableDate": "2026-07-15",
      "availableDateLabel": "July 15, 2026",
      "updatedAt": "2026-06-21T18:35:14-04:00",
      "updatedAtEpochMs": 1782081314000
    },
    {
      "testType": "G2",
      "testCentre": "Toronto Etobicoke",
      "availableDate": "2026-07-14",
      "availableDateLabel": "July 14, 2026",
      "updatedAt": "2026-06-21T21:09:54-04:00",
      "updatedAtEpochMs": 1782090594000
    },
    {
      "testType": "G2",
      "testCentre": "Toronto Port Union",
      "availableDate": "2026-07-20",
      "availableDateLabel": "July 20, 2026",
      "updatedAt": "2026-06-21T19:41:05-04:00",
      "updatedAtEpochMs": 1782085265000
    }
  ]
}
