{
  "generatedAt": "2026-06-30T01:00:17.133067+00:00",
  "sourceDirectory": "../drive-test-assistant/output/downloads",
  "rows": [
    {
      "testType": "G",
      "testCentre": "Hamilton",
      "availableDate": "2026-08-01",
      "availableDateLabel": "August 1, 2026",
      "updatedAt": "2026-06-29T19:30:11.655838-04:00",
      "updatedAtEpochMs": 1782775811655
    },
    {
      "testType": "G",
      "testCentre": "Lindsay",
      "availableDate": "2026-08-05",
      "availableDateLabel": "August 5, 2026",
      "updatedAt": "2026-06-29T19:43:55-04:00",
      "updatedAtEpochMs": 1782776635000
    },
    {
      "testType": "G",
      "testCentre": "Mississauga",
      "availableDate": "2026-08-05",
      "availableDateLabel": "August 5, 2026",
      "updatedAt": "2026-06-29T20:05:29.655838-04:00",
      "updatedAtEpochMs": 1782777929655
    },
    {
      "testType": "G",
      "testCentre": "Newmarket",
      "availableDate": "2026-07-28",
      "availableDateLabel": "July 28, 2026",
      "updatedAt": "2026-06-29T19:33:42.655838-04:00",
      "updatedAtEpochMs": 1782776022655
    },
    {
      "testType": "G",
      "testCentre": "Simcoe",
      "availableDate": "2026-07-22",
      "availableDateLabel": "July 22, 2026",
      "updatedAt": "2026-06-29T19:33:20.655838-04:00",
      "updatedAtEpochMs": 1782776000655
    },
    {
      "testType": "G",
      "testCentre": "Smiths Falls",
      "availableDate": "2026-08-06",
      "availableDateLabel": "August 6, 2026",
      "updatedAt": "2026-06-29T19:38:22.655838-04:00",
      "updatedAtEpochMs": 1782776302655
    },
    {
      "testType": "G",
      "testCentre": "Toronto Downsview",
      "availableDate": "2026-07-14",
      "availableDateLabel": "July 14, 2026",
      "updatedAt": "2026-06-29T20:03:42.655838-04:00",
      "updatedAtEpochMs": 1782777822655
    },
    {
      "testType": "G",
      "testCentre": "Toronto Port Union",
      "availableDate": "2026-08-06",
      "availableDateLabel": "August 6, 2026",
      "updatedAt": "2026-06-29T20:13:16.655838-04:00",
      "updatedAtEpochMs": 1782778396655
    },
    {
      "testType": "G2",
      "testCentre": "Barrie",
      "availableDate": "2026-06-30",
      "availableDateLabel": "June 30, 2026",
      "updatedAt": "2026-06-28T17:58:32-04:00",
      "updatedAtEpochMs": 1782683912000
    },
    {
      "testType": "G2",
      "testCentre": "Lindsay",
      "availableDate": "2026-07-30",
      "availableDateLabel": "July 30, 2026",
      "updatedAt": "2026-06-29T19:58:42.655838-04:00",
      "updatedAtEpochMs": 1782777522655
    },
    {
      "testType": "G2",
      "testCentre": "Newmarket",
      "availableDate": "2026-08-04",
      "availableDateLabel": "August 4, 2026",
      "updatedAt": "2026-06-29T19:39:22-04:00",
      "updatedAtEpochMs": 1782776362000
    },
    {
      "testType": "G2",
      "testCentre": "North Bay",
      "availableDate": "2026-07-27",
      "availableDateLabel": "July 27, 2026",
      "updatedAt": "2026-06-29T19:52:03.655838-04:00",
      "updatedAtEpochMs": 1782777123655
    },
    {
      "testType": "G2",
      "testCentre": "Ottawa Walkley",
      "availableDate": "2026-08-07",
      "availableDateLabel": "August 7, 2026",
      "updatedAt": "2026-06-29T20:02:29.655838-04:00",
      "updatedAtEpochMs": 1782777749655
    },
    {
      "testType": "G2",
      "testCentre": "Renfrew",
      "availableDate": "2026-07-24",
      "availableDateLabel": "July 24, 2026",
      "updatedAt": "2026-06-29T19:31:34.655838-04:00",
      "updatedAtEpochMs": 1782775894655
    },
    {
      "testType": "G2",
      "testCentre": "Smiths Falls",
      "availableDate": "2026-07-31",
      "availableDateLabel": "July 31, 2026",
      "updatedAt": "2026-06-29T20:05:26.655838-04:00",
      "updatedAtEpochMs": 1782777926655
    },
    {
      "testType": "G2",
      "testCentre": "Thunder Bay",
      "availableDate": "2026-08-04",
      "availableDateLabel": "August 4, 2026",
      "updatedAt": "2026-06-28T06:28:53-04:00",
      "updatedAtEpochMs": 1782642533000
    },
    {
      "testType": "G2",
      "testCentre": "Toronto Downsview",
      "availableDate": "2026-07-14",
      "availableDateLabel": "July 14, 2026",
      "updatedAt": "2026-06-29T19:20:09-04:00",
      "updatedAtEpochMs": 1782775209000
    },
    {
      "testType": "G2",
      "testCentre": "Toronto Port Union",
      "availableDate": "2026-08-06",
      "availableDateLabel": "August 6, 2026",
      "updatedAt": "2026-06-29T19:59:11-04:00",
      "updatedAtEpochMs": 1782777551000
    },
    {
      "testType": "G2",
      "testCentre": "Winchester",
      "availableDate": "2026-08-10",
      "availableDateLabel": "August 10, 2026",
      "updatedAt": "2026-06-29T19:53:30.655838-04:00",
      "updatedAtEpochMs": 1782777210655
    }
  ]
}
