{
  "generatedAt": "2026-07-08T22:00:18.610850+00:00",
  "sourceDirectory": "../drive-test-assistant/output/downloads",
  "rows": [
    {
      "testType": "G",
      "testCentre": "Guelph",
      "availableDate": "2026-08-17",
      "availableDateLabel": "August 17, 2026",
      "updatedAt": "2026-07-08T15:34:12-04:00",
      "updatedAtEpochMs": 1783539252000
    },
    {
      "testType": "G",
      "testCentre": "Hamilton",
      "availableDate": "2026-07-10",
      "availableDateLabel": "July 10, 2026",
      "updatedAt": "2026-07-08T14:04:20-04:00",
      "updatedAtEpochMs": 1783533860000
    },
    {
      "testType": "G",
      "testCentre": "Lindsay",
      "availableDate": "2026-08-12",
      "availableDateLabel": "August 12, 2026",
      "updatedAt": "2026-07-08T15:58:30-04:00",
      "updatedAtEpochMs": 1783540710000
    },
    {
      "testType": "G",
      "testCentre": "Mississauga",
      "availableDate": "2026-08-12",
      "availableDateLabel": "August 12, 2026",
      "updatedAt": "2026-07-08T14:27:27-04:00",
      "updatedAtEpochMs": 1783535247000
    },
    {
      "testType": "G",
      "testCentre": "Newmarket",
      "availableDate": "2026-08-18",
      "availableDateLabel": "August 18, 2026",
      "updatedAt": "2026-07-08T15:55:53-04:00",
      "updatedAtEpochMs": 1783540553000
    },
    {
      "testType": "G",
      "testCentre": "Orangeville",
      "availableDate": "2026-07-10",
      "availableDateLabel": "July 10, 2026",
      "updatedAt": "2026-07-08T13:59:19-04:00",
      "updatedAtEpochMs": 1783533559000
    },
    {
      "testType": "G",
      "testCentre": "Smiths Falls",
      "availableDate": "2026-08-11",
      "availableDateLabel": "August 11, 2026",
      "updatedAt": "2026-07-08T16:19:37-04:00",
      "updatedAtEpochMs": 1783541977000
    },
    {
      "testType": "G",
      "testCentre": "Toronto Downsview",
      "availableDate": "2026-08-19",
      "availableDateLabel": "August 19, 2026",
      "updatedAt": "2026-07-08T16:25:28-04:00",
      "updatedAtEpochMs": 1783542328000
    },
    {
      "testType": "G",
      "testCentre": "Toronto Port Union",
      "availableDate": "2026-08-06",
      "availableDateLabel": "August 6, 2026",
      "updatedAt": "2026-07-08T16:28:03-04:00",
      "updatedAtEpochMs": 1783542483000
    },
    {
      "testType": "G2",
      "testCentre": "Brantford",
      "availableDate": "2026-08-10",
      "availableDateLabel": "August 10, 2026",
      "updatedAt": "2026-07-08T14:36:59-04:00",
      "updatedAtEpochMs": 1783535819000
    },
    {
      "testType": "G2",
      "testCentre": "Hamilton",
      "availableDate": "2026-07-13",
      "availableDateLabel": "July 13, 2026",
      "updatedAt": "2026-07-08T14:46:04-04:00",
      "updatedAtEpochMs": 1783536364000
    },
    {
      "testType": "G2",
      "testCentre": "Kitchener",
      "availableDate": "2026-08-13",
      "availableDateLabel": "August 13, 2026",
      "updatedAt": "2026-07-08T14:51:39-04:00",
      "updatedAtEpochMs": 1783536699000
    },
    {
      "testType": "G2",
      "testCentre": "Lindsay",
      "availableDate": "2026-08-12",
      "availableDateLabel": "August 12, 2026",
      "updatedAt": "2026-07-08T16:12:24-04:00",
      "updatedAtEpochMs": 1783541544000
    },
    {
      "testType": "G2",
      "testCentre": "Newmarket",
      "availableDate": "2026-08-11",
      "availableDateLabel": "August 11, 2026",
      "updatedAt": "2026-07-08T15:52:56-04:00",
      "updatedAtEpochMs": 1783540376000
    },
    {
      "testType": "G2",
      "testCentre": "Oakville",
      "availableDate": "2026-08-17",
      "availableDateLabel": "August 17, 2026",
      "updatedAt": "2026-07-08T16:09:29-04:00",
      "updatedAtEpochMs": 1783541369000
    },
    {
      "testType": "G2",
      "testCentre": "Ottawa Canotek",
      "availableDate": "2026-08-18",
      "availableDateLabel": "August 18, 2026",
      "updatedAt": "2026-07-08T16:23:55-04:00",
      "updatedAtEpochMs": 1783542235000
    },
    {
      "testType": "G2",
      "testCentre": "Ottawa Walkley",
      "availableDate": "2026-08-10",
      "availableDateLabel": "August 10, 2026",
      "updatedAt": "2026-07-08T14:23:21-04:00",
      "updatedAtEpochMs": 1783535001000
    },
    {
      "testType": "G2",
      "testCentre": "Renfrew",
      "availableDate": "2026-08-04",
      "availableDateLabel": "August 4, 2026",
      "updatedAt": "2026-07-08T13:41:54-04:00",
      "updatedAtEpochMs": 1783532514000
    },
    {
      "testType": "G2",
      "testCentre": "Smiths Falls",
      "availableDate": "2026-07-09",
      "availableDateLabel": "July 9, 2026",
      "updatedAt": "2026-07-08T16:15:58-04:00",
      "updatedAtEpochMs": 1783541758000
    },
    {
      "testType": "G2",
      "testCentre": "Sudbury",
      "availableDate": "2026-08-13",
      "availableDateLabel": "August 13, 2026",
      "updatedAt": "2026-07-08T13:50:47-04:00",
      "updatedAtEpochMs": 1783533047000
    },
    {
      "testType": "G2",
      "testCentre": "Toronto Downsview",
      "availableDate": "2026-08-19",
      "availableDateLabel": "August 19, 2026",
      "updatedAt": "2026-07-08T16:33:55-04:00",
      "updatedAtEpochMs": 1783542835000
    },
    {
      "testType": "G2",
      "testCentre": "Toronto Etobicoke",
      "availableDate": "2026-07-14",
      "availableDateLabel": "July 14, 2026",
      "updatedAt": "2026-07-08T14:42:13-04:00",
      "updatedAtEpochMs": 1783536133000
    }
  ]
}
