{
  "generatedAt": "2026-06-16T08:00:07.029781+00:00",
  "sourceDirectory": "../drive-test-assistant/output/downloads",
  "rows": [
    {
      "testType": "G",
      "testCentre": "Burlington",
      "availableDate": "2026-07-20",
      "availableDateLabel": "July 20, 2026",
      "updatedAt": "2026-06-15T06:21:51-04:00",
      "updatedAtEpochMs": 1781518911000
    },
    {
      "testType": "G",
      "testCentre": "Guelph",
      "availableDate": "2026-07-08",
      "availableDateLabel": "July 8, 2026",
      "updatedAt": "2026-06-15T12:25:27-04:00",
      "updatedAtEpochMs": 1781540727000
    },
    {
      "testType": "G",
      "testCentre": "Kitchener",
      "availableDate": "2026-06-19",
      "availableDateLabel": "June 19, 2026",
      "updatedAt": "2026-06-15T12:20:30-04:00",
      "updatedAtEpochMs": 1781540430000
    },
    {
      "testType": "G",
      "testCentre": "Lindsay",
      "availableDate": "2026-06-26",
      "availableDateLabel": "June 26, 2026",
      "updatedAt": "2026-06-15T16:26:39-04:00",
      "updatedAtEpochMs": 1781555199000
    },
    {
      "testType": "G",
      "testCentre": "Simcoe",
      "availableDate": "2026-07-13",
      "availableDateLabel": "July 13, 2026",
      "updatedAt": "2026-06-15T05:47:13-04:00",
      "updatedAtEpochMs": 1781516833000
    },
    {
      "testType": "G",
      "testCentre": "Smiths Falls",
      "availableDate": "2026-07-16",
      "availableDateLabel": "July 16, 2026",
      "updatedAt": "2026-06-15T12:15:17-04:00",
      "updatedAtEpochMs": 1781540117000
    },
    {
      "testType": "G",
      "testCentre": "Toronto Downsview",
      "availableDate": "2026-07-16",
      "availableDateLabel": "July 16, 2026",
      "updatedAt": "2026-06-15T16:10:43-04:00",
      "updatedAtEpochMs": 1781554243000
    },
    {
      "testType": "G",
      "testCentre": "Toronto Etobicoke",
      "availableDate": "2026-07-21",
      "availableDateLabel": "July 21, 2026",
      "updatedAt": "2026-06-15T16:22:50-04:00",
      "updatedAtEpochMs": 1781554970000
    },
    {
      "testType": "G",
      "testCentre": "Toronto Port Union",
      "availableDate": "2026-07-21",
      "availableDateLabel": "July 21, 2026",
      "updatedAt": "2026-06-15T12:37:20-04:00",
      "updatedAtEpochMs": 1781541440000
    },
    {
      "testType": "G2",
      "testCentre": "Barrie",
      "availableDate": "2026-07-21",
      "availableDateLabel": "July 21, 2026",
      "updatedAt": "2026-06-15T16:34:24-04:00",
      "updatedAtEpochMs": 1781555664000
    },
    {
      "testType": "G2",
      "testCentre": "Guelph",
      "availableDate": "2026-07-21",
      "availableDateLabel": "July 21, 2026",
      "updatedAt": "2026-06-15T16:27:06-04:00",
      "updatedAtEpochMs": 1781555226000
    },
    {
      "testType": "G2",
      "testCentre": "Lindsay",
      "availableDate": "2026-07-20",
      "availableDateLabel": "July 20, 2026",
      "updatedAt": "2026-06-15T12:09:07-04:00",
      "updatedAtEpochMs": 1781539747000
    },
    {
      "testType": "G2",
      "testCentre": "Newmarket",
      "availableDate": "2026-07-20",
      "availableDateLabel": "July 20, 2026",
      "updatedAt": "2026-06-15T17:01:56-04:00",
      "updatedAtEpochMs": 1781557316000
    },
    {
      "testType": "G2",
      "testCentre": "Oakville",
      "availableDate": "2026-06-19",
      "availableDateLabel": "June 19, 2026",
      "updatedAt": "2026-06-15T16:49:12-04:00",
      "updatedAtEpochMs": 1781556552000
    },
    {
      "testType": "G2",
      "testCentre": "Oshawa",
      "availableDate": "2026-07-15",
      "availableDateLabel": "July 15, 2026",
      "updatedAt": "2026-06-15T16:08:30-04:00",
      "updatedAtEpochMs": 1781554110000
    },
    {
      "testType": "G2",
      "testCentre": "Peterborough",
      "availableDate": "2026-07-07",
      "availableDateLabel": "July 7, 2026",
      "updatedAt": "2026-06-15T15:59:05-04:00",
      "updatedAtEpochMs": 1781553545000
    },
    {
      "testType": "G2",
      "testCentre": "Smiths Falls",
      "availableDate": "2026-06-16",
      "availableDateLabel": "June 16, 2026",
      "updatedAt": "2026-06-15T16:12:31-04:00",
      "updatedAtEpochMs": 1781554351000
    },
    {
      "testType": "G2",
      "testCentre": "Toronto Downsview",
      "availableDate": "2026-07-23",
      "availableDateLabel": "July 23, 2026",
      "updatedAt": "2026-06-15T16:08:01-04:00",
      "updatedAtEpochMs": 1781554081000
    },
    {
      "testType": "G2",
      "testCentre": "Toronto Etobicoke",
      "availableDate": "2026-07-14",
      "availableDateLabel": "July 14, 2026",
      "updatedAt": "2026-06-15T16:09:57-04:00",
      "updatedAtEpochMs": 1781554197000
    },
    {
      "testType": "G2",
      "testCentre": "Toronto Port Union",
      "availableDate": "2026-07-21",
      "availableDateLabel": "July 21, 2026",
      "updatedAt": "2026-06-15T12:15:15-04:00",
      "updatedAtEpochMs": 1781540115000
    }
  ]
}
