{
  "generatedAt": "2026-07-09T13:00:17.728286+00:00",
  "sourceDirectory": "../drive-test-assistant/output/downloads",
  "rows": [
    {
      "testType": "G",
      "testCentre": "Hamilton",
      "availableDate": "2026-07-13",
      "availableDateLabel": "July 13, 2026",
      "updatedAt": "2026-07-09T06:58:41-04:00",
      "updatedAtEpochMs": 1783594721000
    },
    {
      "testType": "G",
      "testCentre": "Lindsay",
      "availableDate": "2026-07-24",
      "availableDateLabel": "July 24, 2026",
      "updatedAt": "2026-07-08T19:07:09-04:00",
      "updatedAtEpochMs": 1783552029000
    },
    {
      "testType": "G",
      "testCentre": "Mississauga",
      "availableDate": "2026-08-13",
      "availableDateLabel": "August 13, 2026",
      "updatedAt": "2026-07-09T07:38:58-04:00",
      "updatedAtEpochMs": 1783597138000
    },
    {
      "testType": "G",
      "testCentre": "Orangeville",
      "availableDate": "2026-08-19",
      "availableDateLabel": "August 19, 2026",
      "updatedAt": "2026-07-09T07:29:40-04:00",
      "updatedAtEpochMs": 1783596580000
    },
    {
      "testType": "G",
      "testCentre": "Oshawa",
      "availableDate": "2026-08-12",
      "availableDateLabel": "August 12, 2026",
      "updatedAt": "2026-07-09T06:45:51-04:00",
      "updatedAtEpochMs": 1783593951000
    },
    {
      "testType": "G",
      "testCentre": "Smiths Falls",
      "availableDate": "2026-08-13",
      "availableDateLabel": "August 13, 2026",
      "updatedAt": "2026-07-08T19:37:48-04:00",
      "updatedAtEpochMs": 1783553868000
    },
    {
      "testType": "G",
      "testCentre": "Toronto Downsview",
      "availableDate": "2026-07-21",
      "availableDateLabel": "July 21, 2026",
      "updatedAt": "2026-07-08T19:36:05-04:00",
      "updatedAtEpochMs": 1783553765000
    },
    {
      "testType": "G",
      "testCentre": "Toronto Port Union",
      "availableDate": "2026-08-17",
      "availableDateLabel": "August 17, 2026",
      "updatedAt": "2026-07-08T19:25:37-04:00",
      "updatedAtEpochMs": 1783553137000
    },
    {
      "testType": "G2",
      "testCentre": "Hamilton",
      "availableDate": "2026-07-22",
      "availableDateLabel": "July 22, 2026",
      "updatedAt": "2026-07-09T07:51:14-04:00",
      "updatedAtEpochMs": 1783597874000
    },
    {
      "testType": "G2",
      "testCentre": "Lindsay",
      "availableDate": "2026-08-12",
      "availableDateLabel": "August 12, 2026",
      "updatedAt": "2026-07-08T19:26:08-04:00",
      "updatedAtEpochMs": 1783553168000
    },
    {
      "testType": "G2",
      "testCentre": "Newmarket",
      "availableDate": "2026-08-18",
      "availableDateLabel": "August 18, 2026",
      "updatedAt": "2026-07-08T19:12:34-04:00",
      "updatedAtEpochMs": 1783552354000
    },
    {
      "testType": "G2",
      "testCentre": "Oakville",
      "availableDate": "2026-08-19",
      "availableDateLabel": "August 19, 2026",
      "updatedAt": "2026-07-08T19:11:06-04:00",
      "updatedAtEpochMs": 1783552266000
    },
    {
      "testType": "G2",
      "testCentre": "Ottawa Canotek",
      "availableDate": "2026-08-19",
      "availableDateLabel": "August 19, 2026",
      "updatedAt": "2026-07-09T07:46:04-04:00",
      "updatedAtEpochMs": 1783597564000
    },
    {
      "testType": "G2",
      "testCentre": "Renfrew",
      "availableDate": "2026-08-04",
      "availableDateLabel": "August 4, 2026",
      "updatedAt": "2026-07-08T19:23:24-04:00",
      "updatedAtEpochMs": 1783553004000
    },
    {
      "testType": "G2",
      "testCentre": "Smiths Falls",
      "availableDate": "2026-08-11",
      "availableDateLabel": "August 11, 2026",
      "updatedAt": "2026-07-08T19:26:30-04:00",
      "updatedAtEpochMs": 1783553190000
    },
    {
      "testType": "G2",
      "testCentre": "Sudbury",
      "availableDate": "2026-08-14",
      "availableDateLabel": "August 14, 2026",
      "updatedAt": "2026-07-09T06:58:10-04:00",
      "updatedAtEpochMs": 1783594690000
    },
    {
      "testType": "G2",
      "testCentre": "Toronto Downsview",
      "availableDate": "2026-07-22",
      "availableDateLabel": "July 22, 2026",
      "updatedAt": "2026-07-08T18:48:31-04:00",
      "updatedAtEpochMs": 1783550911000
    },
    {
      "testType": "G2",
      "testCentre": "Toronto Etobicoke",
      "availableDate": "2026-07-14",
      "availableDateLabel": "July 14, 2026",
      "updatedAt": "2026-07-09T06:50:14-04:00",
      "updatedAtEpochMs": 1783594214000
    },
    {
      "testType": "G2",
      "testCentre": "Toronto Port Union",
      "availableDate": "2026-07-13",
      "availableDateLabel": "July 13, 2026",
      "updatedAt": "2026-07-08T19:07:31-04:00",
      "updatedAtEpochMs": 1783552051000
    }
  ]
}
