{
  "generatedAt": "2026-06-26T00:00:08.618914+00:00",
  "sourceDirectory": "../drive-test-assistant/output/downloads",
  "rows": [
    {
      "testType": "G",
      "testCentre": "Barrie",
      "availableDate": "2026-07-29",
      "availableDateLabel": "July 29, 2026",
      "updatedAt": "2026-06-25T18:41:26.790180-04:00",
      "updatedAtEpochMs": 1782427286790
    },
    {
      "testType": "G",
      "testCentre": "Burlington",
      "availableDate": "2026-07-08",
      "availableDateLabel": "July 8, 2026",
      "updatedAt": "2026-06-25T19:21:46.790180-04:00",
      "updatedAtEpochMs": 1782429706790
    },
    {
      "testType": "G",
      "testCentre": "Hamilton",
      "availableDate": "2026-07-29",
      "availableDateLabel": "July 29, 2026",
      "updatedAt": "2026-06-25T17:17:07-04:00",
      "updatedAtEpochMs": 1782422227000
    },
    {
      "testType": "G",
      "testCentre": "Lindsay",
      "availableDate": "2026-07-24",
      "availableDateLabel": "July 24, 2026",
      "updatedAt": "2026-06-25T17:13:34-04:00",
      "updatedAtEpochMs": 1782422014000
    },
    {
      "testType": "G",
      "testCentre": "Newmarket",
      "availableDate": "2026-08-05",
      "availableDateLabel": "August 5, 2026",
      "updatedAt": "2026-06-25T17:39:12-04:00",
      "updatedAtEpochMs": 1782423552000
    },
    {
      "testType": "G",
      "testCentre": "Simcoe",
      "availableDate": "2026-07-29",
      "availableDateLabel": "July 29, 2026",
      "updatedAt": "2026-06-25T18:42:59.790180-04:00",
      "updatedAtEpochMs": 1782427379790
    },
    {
      "testType": "G",
      "testCentre": "Toronto Downsview",
      "availableDate": "2026-08-04",
      "availableDateLabel": "August 4, 2026",
      "updatedAt": "2026-06-25T18:50:49.790180-04:00",
      "updatedAtEpochMs": 1782427849790
    },
    {
      "testType": "G2",
      "testCentre": "Lindsay",
      "availableDate": "2026-07-29",
      "availableDateLabel": "July 29, 2026",
      "updatedAt": "2026-06-25T17:58:07-04:00",
      "updatedAtEpochMs": 1782424687000
    },
    {
      "testType": "G2",
      "testCentre": "Newmarket",
      "availableDate": "2026-08-04",
      "availableDateLabel": "August 4, 2026",
      "updatedAt": "2026-06-25T17:23:20-04:00",
      "updatedAtEpochMs": 1782422600000
    },
    {
      "testType": "G2",
      "testCentre": "North Bay",
      "availableDate": "2026-07-21",
      "availableDateLabel": "July 21, 2026",
      "updatedAt": "2026-06-25T16:42:59-04:00",
      "updatedAtEpochMs": 1782420179000
    },
    {
      "testType": "G2",
      "testCentre": "Oakville",
      "availableDate": "2026-08-05",
      "availableDateLabel": "August 5, 2026",
      "updatedAt": "2026-06-25T17:17:12-04:00",
      "updatedAtEpochMs": 1782422232000
    },
    {
      "testType": "G2",
      "testCentre": "Ottawa Walkley",
      "availableDate": "2026-07-27",
      "availableDateLabel": "July 27, 2026",
      "updatedAt": "2026-06-25T17:04:59-04:00",
      "updatedAtEpochMs": 1782421499000
    },
    {
      "testType": "G2",
      "testCentre": "Smiths Falls",
      "availableDate": "2026-07-17",
      "availableDateLabel": "July 17, 2026",
      "updatedAt": "2026-06-25T18:30:37.790180-04:00",
      "updatedAtEpochMs": 1782426637790
    },
    {
      "testType": "G2",
      "testCentre": "Thunder Bay",
      "availableDate": "2026-06-26",
      "availableDateLabel": "June 26, 2026",
      "updatedAt": "2026-06-25T16:56:35-04:00",
      "updatedAtEpochMs": 1782420995000
    },
    {
      "testType": "G2",
      "testCentre": "Toronto Downsview",
      "availableDate": "2026-08-04",
      "availableDateLabel": "August 4, 2026",
      "updatedAt": "2026-06-25T17:31:25-04:00",
      "updatedAtEpochMs": 1782423085000
    },
    {
      "testType": "G2",
      "testCentre": "Toronto Etobicoke",
      "availableDate": "2026-07-14",
      "availableDateLabel": "July 14, 2026",
      "updatedAt": "2026-06-25T19:22:07.790180-04:00",
      "updatedAtEpochMs": 1782429727790
    }
  ]
}
